sleepless_agent/__init__.py
sleepless_agent/bot.py
sleepless_agent/claude_code_executor.py
sleepless_agent/claude_executor.py
sleepless_agent/config.py
sleepless_agent/daemon.py
sleepless_agent/git_manager.py
sleepless_agent/models.py
sleepless_agent/monitor.py
sleepless_agent/results.py
sleepless_agent/scheduler.py
sleepless_agent/task_queue.py
sleepless_agent/tools.py
sleepless_agent-0.1.0.dist-info/METADATA
sleepless_agent-0.1.0.dist-info/WHEEL
sleepless_agent-0.1.0.dist-info/entry_points.txt
sleepless_agent-0.1.0.dist-info/top_level.txt
sleepless_agent-0.1.0.dist-info/RECORD
