Metadata-Version: 2.2
Name: sleepless-agent
Version: 0.1.0
Summary: 24/7 AI agent that maximizes Claude usage via Slack interface
Author: Sleepless Agent Maintainers
Project-URL: Homepage, https://github.com/context-machine-lab/sleepless-agent
Project-URL: Repository, https://github.com/context-machine-lab/sleepless-agent
Keywords: ai,automation,agents,slack,anthropic
Classifier: Development Status :: 3 - Alpha
Classifier: Intended Audience :: Developers
Classifier: Operating System :: OS Independent
Classifier: Programming Language :: Python :: 3
Classifier: Programming Language :: Python :: 3.11
Classifier: Topic :: Communications :: Chat
Classifier: Topic :: Office/Business
Requires-Python: >=3.11
Requires-Dist: anthropic>=0.34.4
Requires-Dist: slack-sdk>=4.27.2
Requires-Dist: sqlalchemy>=2.1.5
Requires-Dist: python-dotenv>=1.0.1
Requires-Dist: pydantic>=2.8.2
Requires-Dist: pydantic-settings>=2.3.4
Requires-Dist: gitpython>=3.1.43
Requires-Dist: aiosqlite>=3.2.1
